base/__init__.py
base/memoria.py
gerador/__init__.py
gerador/palavra.py
projeto_teste_upload_pip-0.0.2.dist-info/METADATA
projeto_teste_upload_pip-0.0.2.dist-info/WHEEL
projeto_teste_upload_pip-0.0.2.dist-info/top_level.txt
projeto_teste_upload_pip-0.0.2.dist-info/RECORD
