Metadata-Version: 2.1
Name: projeto-teste-upload-pip
Version: 0.0.2
Summary: Projeto para a faculdade.
Author: Bruno Kalel
Author-email: brunokalel@icluoud.com
Keywords: python
Classifier: Development Status :: 1 - Planning
Classifier: Intended Audience :: Developers
Classifier: Programming Language :: Python :: 3
Classifier: Operating System :: Unix
Classifier: Operating System :: MacOS :: MacOS X
Classifier: Operating System :: Microsoft :: Windows
